json_corrector/__init__.py
json_corrector/jc.py
json_corrector/jc_wrapper.py
json_corrector-3.0.4.dist-info/LICENSE
json_corrector-3.0.4.dist-info/METADATA
json_corrector-3.0.4.dist-info/WHEEL
json_corrector-3.0.4.dist-info/entry_points.txt
json_corrector-3.0.4.dist-info/top_level.txt
json_corrector-3.0.4.dist-info/RECORD
