Metadata-Version: 2.2
Name: json_corrector
Version: 3.0.4
Summary: Takes data, that is almost in json format, and converts it to json data. Thus prepare the data for a json parser.
Author-email: tschenkelz <tschenkelpieper@gmail.com>
License: MIT
Project-URL: Homepage, https://github.com/tschenkelz/json_corrector
Project-URL: Issues, https://github.com/tschenkelz/json_corrector/issues
Classifier: Programming Language :: Python :: 3
Classifier: Operating System :: OS Independent
Requires-Python: >=3.8
License-File: LICENSE
